verba_rag/__init__.py
verba_rag/ingestion/__init__.py
verba_rag/ingestion/cli.py
verba_rag/ingestion/fetch_github.py
verba_rag/ingestion/import_data.py
verba_rag/ingestion/import_weaviate.py
verba_rag/ingestion/init_cache.py
verba_rag/ingestion/init_schema.py
verba_rag/ingestion/init_suggestion.py
verba_rag/ingestion/preprocess.py
verba_rag/ingestion/preprocess_weaviate.py
verba_rag/ingestion/util.py
verba_rag/retrieval/__init__.py
verba_rag/retrieval/advanced_engine.py
verba_rag/retrieval/interface.py
verba_rag/retrieval/simple_engine.py
verba_rag/server/__init__.py
verba_rag/server/api.py
verba_rag/server/cli.py
verba_rag/server/frontend/out/404.html
verba_rag/server/frontend/out/about.html
verba_rag/server/frontend/out/background.png
verba_rag/server/frontend/out/document_explorer.html
verba_rag/server/frontend/out/favicon.ico
verba_rag/server/frontend/out/favicon.png
verba_rag/server/frontend/out/index.html
verba_rag/server/frontend/out/next.svg
verba_rag/server/frontend/out/verba.png
verba_rag/server/frontend/out/vercel.svg
verba_rag/server/frontend/out/_next/static/0Hcan7GeSF1TuouAgzveb/_buildManifest.js
verba_rag/server/frontend/out/_next/static/0Hcan7GeSF1TuouAgzveb/_ssgManifest.js
verba_rag/server/frontend/out/_next/static/5fzR3LERKY5UlE9ayIEWy/_buildManifest.js
verba_rag/server/frontend/out/_next/static/5fzR3LERKY5UlE9ayIEWy/_ssgManifest.js
verba_rag/server/frontend/out/_next/static/BrKix8hVmzKkq4nA40XDY/_buildManifest.js
verba_rag/server/frontend/out/_next/static/BrKix8hVmzKkq4nA40XDY/_ssgManifest.js
verba_rag/server/frontend/out/_next/static/E3xJxzpNDa7hQ9ErbEuyX/_buildManifest.js
verba_rag/server/frontend/out/_next/static/E3xJxzpNDa7hQ9ErbEuyX/_ssgManifest.js
verba_rag/server/frontend/out/_next/static/Ej9O_hZ3RDAnJYJlOxclF/_buildManifest.js
verba_rag/server/frontend/out/_next/static/Ej9O_hZ3RDAnJYJlOxclF/_ssgManifest.js
verba_rag/server/frontend/out/_next/static/GGmsoX3roagotCYtIHhEK/_buildManifest.js
verba_rag-0.2.2.dist-info/LICENSE
verba_rag-0.2.2.dist-info/METADATA
verba_rag-0.2.2.dist-info/WHEEL
verba_rag-0.2.2.dist-info/entry_points.txt
verba_rag-0.2.2.dist-info/top_level.txt
verba_rag-0.2.2.dist-info/RECORD
