Metadata-Version: 2.1
Name: verba-rag
Version: 0.2.2
Summary: Welcome to Verba: The Golden RAGtriever, an open-source initiative designed to offer a streamlined, user-friendly interface for Retrieval-Augmented Generation (RAG) applications. In just a few easy steps, dive into your data and make meaningful interactions!
Home-page: https://github.com/weaviate/Verba
Author: Weaviate
Author-email: edward@weaviate.io
Classifier: License :: OSI Approved :: BSD License
Classifier: Programming Language :: Python :: 3
Classifier: Programming Language :: Python :: 3.6
Classifier: Programming Language :: Python :: 3.7
Classifier: Programming Language :: Python :: 3.8
Classifier: Programming Language :: Python :: 3.9
Classifier: Programming Language :: Python :: 3.10
License-File: LICENSE
Requires-Dist: weaviate-client >=3.23.1
Requires-Dist: python-dotenv >=1.0.0
Requires-Dist: openai >=0.27.9
Requires-Dist: wasabi >=1.1.2
Requires-Dist: spacy
Requires-Dist: fastapi >=0.102.0
Requires-Dist: uvicorn[standard]
Requires-Dist: click >=8.1.7
Provides-Extra: dev
Requires-Dist: pytest ; extra == 'dev'
Requires-Dist: wheel ; extra == 'dev'
Requires-Dist: twine ; extra == 'dev'
Requires-Dist: black ; extra == 'dev'
Requires-Dist: setuptools ; extra == 'dev'
